[{"origin": [4614, 4150], "building": "0030", "dimensions": [4925, 6545], "level": "1", "number": "611", "polygon": [[[28, 0]], [[28, 44]], [[1, 45]], [[0, 335]], [[454, 335]], [[454, 0]]]}, {"origin": [5069, 4150], "building": "0030", "dimensions": [4925, 6545], "level": "1", "number": "611", "polygon": [[[19, 0]], [[5, 236]], [[25, 249]], [[54, 185]], [[125, 157]], [[126, 249]], [[160, 238]], [[160, 404]], [[102, 405]], [[102, 464]], [[150, 563]], [[84, 588]], [[160, 669]], [[270, 669]], [[307, 648]], [[506, 648]], [[543, 669]], [[614, 669]], [[614, 579]], [[701, 572]], [[755, 517]], [[756, 308]], [[702, 252]], [[614, 245]], [[614, 131]], [[160, 131]], [[146, 143]], [[140, 0]]]}, {"origin": [78, 916], "building": "0030", "dimensions": [4925, 6545], "level": "1", "number": "112", "polygon": [[[0, 19]], [[0, 123]], [[28, 123]], [[38, 158]], [[30, 393]], [[0, 395]], [[0, 445]], [[89, 445]], [[91, 500]], [[138, 501]], [[513, 500]], [[514, 448]], [[600, 448]], [[600, 19]], [[568, 19]], [[564, 5]], [[472, 5]], [[470, 19]], [[184, 19]], [[181, 5]], [[89, 5]], [[86, 19]]]}, {"origin": [5772, 866], "building": "0030", "dimensions": [4925, 6545], "level": "1", "number": "412", "polygon": [[[0, 1]], [[1, 305]], [[431, 305]], [[433, 249]], [[451, 250]], [[452, 305]], [[541, 305]], [[541, 104]], [[451, 104]], [[451, 163]], [[433, 164]], [[431, 103]], [[328, 0]]]}, {"origin": [5170, 868], "building": "0030", "dimensions": [4925, 6545], "level": "1", "number": "411", "polygon": [[[0, 0]], [[0, 549]], [[20, 550]], [[19, 568]], [[0, 569]], [[0, 703]], [[180, 703]], [[180, 657]], [[159, 654]], [[159, 569]], [[112, 569]], [[111, 549]], [[532, 548]], [[533, 392]], [[510, 386]], [[502, 152]], [[511, 118]], [[583, 107]], [[583, 16]], [[540, 15]], [[539, 0]]]}, {"origin": [4614, 4505], "building": "0030", "dimensions": [4925, 6545], "level": "1", "number": "611", "polygon": [[[0, 0]], [[0, 315]], [[46, 315]], [[49, 342]], [[594, 342]], [[595, 300]], [[535, 240]], [[515, 253]], [[488, 194]], [[454, 191]], [[454, 0]]]}, {"origin": [1545, 241], "building": "0030", "dimensions": [4925, 6545], "level": "1", "number": "212", "polygon": [[[319, 1]], [[67, 1]], [[66, 40]], [[0, 40]], [[0, 561]], [[55, 561]], [[57, 468]], [[110, 481]], [[168, 455]], [[169, 428]], [[319, 428]]]}, {"origin": [1884, 241], "building": "0030", "dimensions": [4925, 6545], "level": "1", "number": "212", "polygon": [[[317, 0]], [[0, 1]], [[0, 561]], [[10, 469]], [[63, 481]], [[121, 453]], [[122, 428]], [[318, 428]]]}, {"origin": [2222, 241], "building": "0030", "dimensions": [4925, 6545], "level": "1", "number": "211", "polygon": [[[0, 0]], [[0, 427]], [[204, 427]], [[206, 454]], [[262, 479]], [[311, 469]], [[320, 561]], [[321, 2]]]}, {"origin": [2562, 241], "building": "0030", "dimensions": [4925, 6545], "level": "1", "number": "211", "polygon": [[[0, 1]], [[0, 428]], [[152, 428]], [[153, 455]], [[211, 481]], [[265, 469]], [[267, 561]], [[319, 561]], [[320, 2]]]}, {"origin": [2935, 241], "building": "0030", "dimensions": [4925, 6545], "level": "1", "number": "312", "polygon": [[[319, 1]], [[0, 1]], [[0, 561]], [[53, 561]], [[55, 468]], [[108, 481]], [[166, 455]], [[168, 428]], [[319, 428]]]}, {"origin": [3274, 241], "building": "0030", "dimensions": [4925, 6545], "level": "1", "number": "312", "polygon": [[[321, 1]], [[0, 1]], [[0, 561]], [[9, 469]], [[58, 479]], [[115, 453]], [[116, 427]], [[321, 427]]]}, {"origin": [3615, 241], "building": "0030", "dimensions": [4925, 6545], "level": "1", "number": "311", "polygon": [[[0, 1]], [[0, 428]], [[196, 429]], [[191, 459]], [[62, 449]], [[61, 549]], [[190, 545]], [[197, 561]], [[317, 561]], [[317, 0]]]}, {"origin": [3952, 241], "building": "0030", "dimensions": [4925, 6545], "level": "1", "number": "311", "polygon": [[[1, 0]], [[0, 428]], [[150, 428]], [[152, 456]], [[0, 448]], [[0, 561]], [[132, 561]], [[139, 545]], [[152, 561]], [[318, 561]], [[318, 1]]]}, {"origin": [4312, 241], "building": "0030", "dimensions": [4925, 6545], "level": "1", "number": "414", "polygon": [[[0, 1]], [[0, 561]], [[123, 561]], [[125, 546]], [[141, 546]], [[143, 561]], [[239, 561]], [[239, 445]], [[142, 445]], [[124, 457]], [[123, 427]], [[310, 425]], [[310, 48]], [[263, 48]], [[261, 1]]]}, {"origin": [4571, 241], "building": "0030", "dimensions": [4925, 6545], "level": "1", "number": "414", "polygon": [[[350, 1]], [[71, 1]], [[71, 425]], [[114, 425]], [[116, 454]], [[0, 445]], [[0, 561]], [[96, 561]], [[98, 545]], [[116, 561]], [[238, 561]], [[240, 424]], [[394, 424]], [[394, 253]], [[350, 251]]]}, {"origin": [5772, 241], "building": "0030", "dimensions": [4925, 6545], "level": "1", "number": "412", "polygon": [[[0, 295]], [[334, 295]], [[432, 205]], [[434, 145]], [[457, 154]], [[541, 133]], [[541, 1]], [[452, 1]], [[450, 57]], [[432, 55]], [[432, 1]], [[0, 1]]]}, {"origin": [5088, 3146], "building": "0030", "dimensions": [4925, 6545], "level": "1", "number": "613", "polygon": [[[455, 0]], [[303, 0]], [[302, 61]], [[189, 61]], [[126, 129]], [[124, 159]], [[75, 160]], [[73, 226]], [[0, 226]], [[0, 534]], [[200, 534]], [[201, 554]], [[152, 554]], [[152, 640]], [[303, 640]], [[291, 537]], [[323, 534]], [[322, 129]], [[453, 16]]]}, {"origin": [826, 76], "building": "0030", "dimensions": [4925, 6545], "level": "1", "number": "111", "polygon": [[[1, 1]], [[0, 476]], [[196, 477]], [[196, 726]], [[321, 726]], [[323, 646]], [[341, 648]], [[341, 726]], [[427, 726]], [[427, 496]], [[341, 496]], [[341, 555]], [[321, 556]], [[321, 0]]]}, {"origin": [4614, 2246], "building": "0030", "dimensions": [4925, 6545], "level": "1", "number": "511", "polygon": [[[44, 0]], [[44, 242]], [[57, 244]], [[57, 276]], [[28, 278]], [[28, 319]], [[0, 322]], [[1, 599]], [[35, 598]], [[37, 506]], [[101, 529]], [[138, 599]], [[354, 598]], [[358, 612]], [[449, 612]], [[453, 598]], [[663, 598]], [[663, 277]], [[511, 277]], [[510, 257]], [[402, 257]], [[401, 277]], [[340, 277]], [[339, 244]], [[356, 243]], [[356, 52]], [[221, 52]], [[218, 0]]]}, {"origin": [1167, 76], "building": "0030", "dimensions": [4925, 6545], "level": "1", "number": "111", "polygon": [[[0, 0]], [[0, 476]], [[211, 477]], [[210, 557]], [[191, 556]], [[191, 496]], [[105, 496]], [[105, 726]], [[191, 726]], [[193, 646]], [[211, 648]], [[211, 726]], [[338, 726]], [[338, 166]], [[316, 164]], [[316, 1]]]}, {"origin": [4990, 76], "building": "0030", "dimensions": [4925, 6545], "level": "1", "number": "413", "polygon": [[[2, 1]], [[2, 151]], [[52, 151]], [[61, 190]], [[61, 389]], [[52, 418]], [[0, 418]], [[0, 567]], [[408, 567]], [[409, 319]], [[423, 316]], [[409, 1]]]}, {"origin": [5419, 77], "building": "0030", "dimensions": [4925, 6545], "level": "1", "number": "413", "polygon": [[[0, 0]], [[0, 144]], [[11, 146]], [[0, 164]], [[0, 566]], [[298, 566]], [[299, 165]], [[83, 164]], [[87, 0]]]}, {"origin": [5430, 3146], "building": "0030", "dimensions": [4925, 6545], "level": "1", "number": "612", "polygon": [[[133, 0]], [[133, 22]], [[0, 141]], [[0, 529]], [[164, 530]], [[166, 554]], [[223, 580]], [[274, 568]], [[284, 661]], [[284, 0]]]}, {"origin": [77, 380], "building": "0030", "dimensions": [4925, 6545], "level": "1", "number": "112", "polygon": [[[1, 1]], [[1, 535]], [[313, 535]], [[315, 520]], [[331, 520]], [[333, 535]], [[443, 535]], [[442, 424]], [[313, 429]], [[313, 1]]]}, {"origin": [410, 380], "building": "0030", "dimensions": [4925, 6545], "level": "1", "number": "112", "polygon": [[[0, 1]], [[0, 405]], [[128, 405]], [[130, 535]], [[268, 535]], [[268, 410]], [[396, 408]], [[398, 288]], [[593, 297]], [[593, 192]], [[396, 197]], [[397, 1]]]}, {"origin": [4953, 2864], "building": "0030", "dimensions": [4925, 6545], "level": "1", "number": "511", "polygon": [[[0, 0]], [[0, 328]], [[156, 328]], [[156, 348]], [[89, 348]], [[89, 396]], [[206, 396]], [[247, 351]], [[247, 329]], [[268, 328]], [[324, 266]], [[324, 0]]]}, {"origin": [4614, 3234], "building": "0030", "dimensions": [4925, 6545], "level": "1", "number": "613", "polygon": [[[0, 0]], [[0, 521]], [[66, 522]], [[67, 572]], [[454, 572]], [[454, 437]], [[468, 433]], [[454, 113]], [[164, 113]], [[162, 0]]]}, {"origin": [4614, 2757], "building": "0030", "dimensions": [4925, 6545], "level": "1", "number": "511", "polygon": [[[40, 0]], [[40, 101]], [[0, 107]], [[1, 435]], [[217, 435]], [[211, 495]], [[369, 495]], [[369, 455]], [[308, 454]], [[319, 435]], [[319, 107]], [[134, 107]], [[108, 31]]]}, {"origin": [5772, 449], "building": "0030", "dimensions": [4925, 6545], "level": "1", "number": "412", "polygon": [[[695, 8]], [[449, 8]], [[360, 89]], [[358, 107]], [[308, 107]], [[305, 93]], [[0, 107]], [[0, 256]], [[52, 289]], [[76, 360]], [[0, 360]], [[0, 397]], [[209, 397]], [[213, 411]], [[356, 397]], [[358, 419]], [[439, 501]], [[695, 501]]]}, {"origin": [5243, 3719], "building": "0030", "dimensions": [4925, 6545], "level": "1", "number": "612", "polygon": [[[458, 0]], [[386, 36]], [[362, 108]], [[0, 108]], [[0, 542]], [[471, 542]], [[471, 108]], [[458, 101]]]}, {"origin": [1022, 803], "building": "0030", "dimensions": [4925, 6545], "level": "1", "number": "111", "polygon": [[[18, 5]], [[0, 19]], [[0, 776]], [[483, 776]], [[483, 453]], [[434, 453]], [[425, 415]], [[425, 217]], [[435, 183]], [[483, 183]], [[483, 19]], [[466, 5]], [[374, 5]], [[370, 19]], [[113, 19]], [[109, 5]]]}, {"origin": [1545, 714], "building": "0030", "dimensions": [4925, 6545], "level": "1", "number": "212", "polygon": [[[59, 0]], [[58, 106]], [[0, 108]], [[0, 272]], [[48, 272]], [[58, 306]], [[58, 504]], [[48, 542]], [[0, 542]], [[0, 659]], [[82, 659]], [[84, 702]], [[482, 702]], [[482, 661]], [[497, 659]], [[497, 108]], [[448, 108]], [[421, 32]], [[357, 0]], [[349, 108]], [[155, 108]], [[130, 34]]]}, {"origin": [2386, 714], "building": "0030", "dimensions": [4925, 6545], "level": "1", "number": "211", "polygon": [[[100, 12]], [[64, 48]], [[48, 108]], [[0, 108]], [[0, 665]], [[47, 665]], [[50, 702]], [[506, 702]], [[506, 542]], [[457, 542]], [[448, 504]], [[456, 272]], [[496, 272]], [[496, 108]], [[439, 106]], [[438, 0]], [[368, 33]], [[343, 108]], [[147, 108]], [[144, 0]]]}, {"origin": [2934, 714], "building": "0030", "dimensions": [4925, 6545], "level": "1", "number": "312", "polygon": [[[59, 0]], [[59, 101]], [[10, 108]], [[10, 195]], [[85, 196]], [[85, 280]], [[52, 281]], [[58, 504]], [[48, 542]], [[0, 542]], [[0, 703]], [[437, 702]], [[439, 646]], [[496, 646]], [[496, 108]], [[448, 108]], [[433, 49]], [[395, 11]], [[357, 0]], [[349, 108]], [[154, 108]], [[130, 35]]]}, {"origin": [3774, 803], "building": "0030", "dimensions": [4925, 6545], "level": "1", "number": "311", "polygon": [[[0, 19]], [[0, 613]], [[94, 613]], [[96, 675]], [[146, 723]], [[354, 723]], [[404, 674]], [[406, 613]], [[496, 613]], [[496, 453]], [[447, 453]], [[438, 415]], [[438, 217]], [[448, 183]], [[496, 183]], [[496, 19]], [[442, 19]], [[438, 5]], [[346, 5]], [[342, 19]], [[53, 5]], [[49, 19]]]}, {"origin": [4312, 803], "building": "0030", "dimensions": [4925, 6545], "level": "1", "number": "414", "polygon": [[[15, 5]], [[0, 19]], [[0, 183]], [[50, 184]], [[58, 415]], [[49, 453]], [[0, 453]], [[0, 613]], [[301, 613]], [[303, 792]], [[497, 792]], [[497, 630]], [[457, 628]], [[457, 558]], [[497, 557]], [[497, 19]], [[483, 5]], [[391, 5]], [[387, 19]], [[111, 19]], [[107, 5]]]}]