[{"origin": [531, 1627], "building": "0053", "dimensions": [4931, 1130], "level": "4", "number": "241", "polygon": [[[0, 0]], [[0, 617]], [[187, 617]], [[187, 521]], [[215, 520]], [[216, 434]], [[279, 460]], [[307, 520]], [[531, 519]], [[531, 95]], [[385, 95]], [[383, 0]], [[143, 0]], [[141, 13]], [[118, 13]], [[116, 0]]]}, {"origin": [385, 2280], "building": "0053", "dimensions": [4931, 1130], "level": "4", "number": "242", "polygon": [[[0, 139]], [[0, 431]], [[623, 431]], [[623, 259]], [[532, 257]], [[533, 1]], [[246, 0]], [[218, 70]], [[150, 103]], [[148, 139]]]}, {"origin": [387, 2749], "building": "0053", "dimensions": [4931, 1130], "level": "4", "number": "142", "polygon": [[[0, 0]], [[0, 446]], [[256, 446]], [[257, 428]], [[281, 428]], [[283, 446]], [[622, 445]], [[622, 335]], [[531, 334]], [[531, 106]], [[444, 104]], [[445, 88]], [[531, 88]], [[531, 0]], [[346, 0]], [[352, 106]], [[327, 104]], [[327, 0]]]}, {"origin": [241, 4138], "building": "0053", "dimensions": [4931, 1130], "level": "4", "number": "141", "polygon": [[[0, 70]], [[0, 725]], [[627, 725]], [[627, 499]], [[665, 497]], [[665, 397]], [[695, 396]], [[717, 341]], [[788, 311]], [[788, 396]], [[821, 396]], [[821, 69]], [[357, 69]], [[355, 0]], [[144, 0]], [[144, 68]], [[121, 70]], [[120, 155]], [[67, 139]], [[28, 70]]]}, {"origin": [213, 67], "building": "0053", "dimensions": [4931, 1130], "level": "4", "number": "244", "polygon": [[[0, 1]], [[0, 504]], [[266, 504]], [[268, 603]], [[390, 603]], [[390, 508]], [[420, 507]], [[460, 437]], [[512, 422]], [[513, 507]], [[551, 509]], [[541, 726]], [[554, 743]], [[541, 745]], [[541, 1090]], [[529, 1101]], [[590, 1126]], [[625, 1207]], [[529, 1207]], [[529, 1218]], [[795, 1218]], [[795, 1105]], [[669, 1104]], [[669, 850]], [[611, 825]], [[584, 757]], [[669, 755]], [[656, 743]], [[669, 726]], [[669, 526]], [[653, 524]], [[653, 508]], [[682, 506]], [[682, 1]]]}, {"origin": [529, 3213], "building": "0053", "dimensions": [4931, 1130], "level": "4", "number": "143", "polygon": [[[0, 0]], [[0, 584]], [[120, 584]], [[121, 568]], [[145, 568]], [[147, 584]], [[391, 584]], [[393, 543]], [[479, 544]], [[479, 373]], [[390, 371]], [[391, 0]]]}, {"origin": [67, 696], "building": "0053", "dimensions": [4931, 1130], "level": "4", "number": "243", "polygon": [[[1, 0]], [[1, 367]], [[144, 366]], [[146, 444]], [[668, 444]], [[668, 85]], [[570, 85]], [[568, 0]]]}]