[{"origin": [227, 233], "building": "DICKINSON", "floor": "2", "polygon": [[[0, 0]], [[1, 6139]], [[8241, 6139]], [[8242, 5090]], [[9739, 5090]], [[9739, 332]], [[8245, 332]], [[8244, 0]]], "number": "20"}, {"origin": [3174, 2915], "building": "DICKINSON", "floor": "2", "polygon": [[[871, 0]], [[581, 0]], [[580, 176]], [[318, 176]], [[303, 252]], [[259, 316]], [[118, 176]], [[2, 176]], [[2, 897]], [[422, 897]], [[424, 911]], [[586, 911]], [[587, 897]], [[644, 897]], [[645, 911]], [[808, 911]], [[809, 897]], [[835, 897]], [[835, 248]], [[871, 246]]], "number": "25"}, {"origin": [4688, 2874], "building": "DICKINSON", "floor": "2", "polygon": [[[115, 0]], [[115, 361]], [[0, 363]], [[0, 938]], [[168, 938]], [[170, 952]], [[330, 952]], [[331, 938]], [[381, 938]], [[383, 952]], [[958, 938]], [[958, 178]], [[891, 178]], [[749, 319]], [[704, 250]], [[690, 178]], [[580, 177]], [[580, 0]]], "number": "22"}, {"origin": [4431, 1339], "building": "DICKINSON", "floor": "2", "polygon": [[[0, 1]], [[0, 1218]], [[416, 1218]], [[418, 1070]], [[863, 1070]], [[865, 1085]], [[911, 1085]], [[925, 1011]], [[970, 943]], [[1112, 1085]], [[1218, 1085]], [[1217, 1]]], "number": "23"}, {"origin": [3174, 1339], "building": "DICKINSON", "floor": "2", "polygon": [[[2, 1]], [[2, 796]], [[95, 796]], [[96, 839]], [[1040, 839]], [[1040, 1]]], "number": "24"}, {"origin": [9225, 5705], "building": "DICKINSON", "floor": "2", "polygon": [[[0, 0]], [[0, 181]], [[741, 181]], [[741, 0]]], "number": "15"}, {"origin": [9225, 5893], "building": "DICKINSON", "floor": "2", "polygon": [[[0, 0]], [[0, 181]], [[741, 180]], [[741, 0]]], "number": "16"}]